first_pack20180828/__init__.py
first_pack20180828/first_pack20180828.py
first_pack20180828-0.0.1.dist-info/LICENSE.txt
first_pack20180828-0.0.1.dist-info/METADATA
first_pack20180828-0.0.1.dist-info/RECORD
first_pack20180828-0.0.1.dist-info/WHEEL
first_pack20180828-0.0.1.dist-info/top_level.txt
