Metadata-Version: 2.1
Name: first-pack20180828
Version: 0.0.1
Summary: A first simole Python project
Home-page: UNKNOWN
Author: donabe
Author-email: taiga202500@gmail.com
License: UNKNOWN
Platform: UNKNOWN
